UnifiedAI/__init__.py
UnifiedAI/api.py
UnifiedAI/claude.py
UnifiedAI/gemini.py
UnifiedAI/gpt.py
UnifiedAI/ollama.py
UnifiedAI/unified.py
unifiedai-1.5.5.dist-info/licenses/LICENSE
unifiedai-1.5.5.dist-info/METADATA
unifiedai-1.5.5.dist-info/WHEEL
unifiedai-1.5.5.dist-info/top_level.txt
unifiedai-1.5.5.dist-info/RECORD
