Metadata-Version: 2.4
Name: UnifiedAI
Version: 1.5.5
Summary: A python package that simplifies and unifies the usage of multiple AI APIs
Project-URL: Homepage, https://github.com/TovbinZ/UnifiedAI
Classifier: Programming Language :: Python :: 3
Classifier: License :: OSI Approved :: MIT License
Classifier: Operating System :: OS Independent
Requires-Python: >=3.11
License-File: LICENSE
Requires-Dist: grpcio==1.60.1
Requires-Dist: httpx==0.27.2
Requires-Dist: openai==1.35.8
Requires-Dist: google-generativeai
Requires-Dist: anthropic==0.40.0
Requires-Dist: ollama==0.4.6
Dynamic: license-file
